email_helpers/__init__.py
email_helpers/gmail_helpers.py
email_helpers/tests/__init__.py
ctodd_python_lib_email-1.0.1.dist-info/LICENSE
ctodd_python_lib_email-1.0.1.dist-info/METADATA
ctodd_python_lib_email-1.0.1.dist-info/WHEEL
ctodd_python_lib_email-1.0.1.dist-info/top_level.txt
ctodd_python_lib_email-1.0.1.dist-info/RECORD
