Metadata-Version: 2.1
Name: ctodd-python-lib-email
Version: 1.0.1
Summary: Python utilities used for interacting with email clients and sending emails
Home-page: https://github.com/ChristopherHaydenTodd/ctodd-python-lib-email
Author: Christopher H. Todd
Author-email: Christopher.Hayden.Todd@gmail.com
License: MIT
Keywords: python,libraries,gmail,email
Platform: UNKNOWN
Classifier: Development Status :: 5 - Production/Stable
Classifier: Intended Audience :: Developers
Classifier: Natural Language :: English
Classifier: Programming Language :: Python
Classifier: Programming Language :: Python :: 3
Classifier: Programming Language :: Python :: 3.6
Classifier: Programming Language :: Python :: 3.7
Classifier: Programming Language :: Python :: 3.8
Requires-Python: >3.6
Requires-Dist: google-api-python-client (==1.7.9)
Requires-Dist: oauthlib (==3.0.2)
Requires-Dist: google-auth-oauthlib (==0.4.0)
Requires-Dist: google-auth (==1.6.3)
Requires-Dist: google-auth-httplib2 (==0.0.3)
